tinycio/__init__.py
tinycio/balance.py
tinycio/codec.py
tinycio/colorspace.py
tinycio/correction.py
tinycio/globals.py
tinycio/loss.py
tinycio/lut.py
tinycio/spectral.py
tinycio/tonemapping.py
tinycio/usertypes.py
tinycio/fsio/__init__.py
tinycio/fsio/format.py
tinycio/fsio/imagefile.py
tinycio/fsio/lutfile.py
tinycio/np_agx/agx.py
tinycio/numerics/__init__.py
tinycio/numerics/linalg.py
tinycio/numerics/util_pt.py
tinycio/numerics/util_py.py
tinycio/numerics/vector.py
tinycio/scripts/__init__.py
tinycio/scripts/color2color.py
tinycio/scripts/hdr_codec.py
tinycio/scripts/img2cube.py
tinycio/scripts/post_install.py
tinycio/scripts/white_balance.py
tinycio/util/__init__.py
tinycio/util/colorutil.py
tinycio/util/const.py
tinycio/util/curve.py
tinycio/util/miscutil.py
tinycio-0.8.1.dist-info/LICENSE.txt
tinycio-0.8.1.dist-info/METADATA
tinycio-0.8.1.dist-info/WHEEL
tinycio-0.8.1.dist-info/entry_points.txt
tinycio-0.8.1.dist-info/top_level.txt
tinycio-0.8.1.dist-info/RECORD
