Metadata-Version: 2.1
Name: tinycio
Version: 0.8.1
Summary: A primitive, lightweight color management framework for PyTorch-involved projects
Author-email: Sam Izdat <ghsamizdat@gmail.com>
Project-URL: Homepage, https://sam-izdat.github.io/tinycio
Project-URL: Issues, https://github.com/Sam-Izdat/tinycio/issues
Classifier: Programming Language :: Python :: 3
Classifier: License :: OSI Approved :: MIT License
Classifier: Operating System :: OS Independent
Requires-Python: >=3.8
License-File: LICENSE.txt
Requires-Dist: numpy >=1.21
Requires-Dist: imageio >=2.9
Requires-Dist: toml >=0.10
Requires-Dist: tqdm >=4.64
